flex_dispatch/__init__.py
flex_dispatch-0.1.1.dist-info/WHEEL
flex_dispatch-0.1.1.dist-info/METADATA
flex_dispatch-0.1.1.dist-info/RECORD
