Metadata-Version: 2.1
Name: flex-dispatch
Version: 0.1.1
Summary: Dynamic dispatch for python similar to clojure's multimethod.
Home-page: https://github.com/cblades/flex_dispatch
License: Apache 2.0
Author: Chris Blades
Author-email: chrisdblades@gmail.com
Requires-Python: >=3.6,<4.0
Classifier: License :: Other/Proprietary License
Classifier: Programming Language :: Python :: 3
Classifier: Programming Language :: Python :: 3.10
Classifier: Programming Language :: Python :: 3.6
Classifier: Programming Language :: Python :: 3.7
Classifier: Programming Language :: Python :: 3.8
Classifier: Programming Language :: Python :: 3.9
